RobotRaconteur/Client.py
RobotRaconteur/NamedClient.py
RobotRaconteur/RobotRaconteurPython.py
RobotRaconteur/RobotRaconteurPythonDataTypes.py
RobotRaconteur/RobotRaconteurPythonError.py
RobotRaconteur/RobotRaconteurPythonUtil.py
RobotRaconteur/_RobotRaconteurPython.pyd
RobotRaconteur/__init__.py
RobotRaconteur/classproperty.py
robotraconteur-1.2.7.dist-info/METADATA
robotraconteur-1.2.7.dist-info/WHEEL
robotraconteur-1.2.7.dist-info/top_level.txt
robotraconteur-1.2.7.dist-info/RECORD
