Metadata-Version: 2.1
Name: robotraconteur
Version: 1.2.7
Summary: Robot Raconteur Python Library
Home-page: http://robotraconteur.com/
Author: John Wason
Author-email: wason@wasontech.com
License: Apache-2.0
Platform: UNKNOWN
Requires-Dist: numpy
